Workbook

Sheet Leads
A1: CONTROLE DE LEADS — Kitnets & Apartamentos UFSC
A2: Preencher as colunas A–I a cada novo lead (L e M com dados da campanha do dia). As demais calculam sozinhas.
A4: ID_Lead | B4: Data_Entrada | C4: Nome | D4: WhatsApp | E4: Canal_Origem | F4: Público | G4: Unidade_Interesse | H4: Status_Funil | I4: Data_Ultimo_Contato | J4: Minutos_p/_1a_Resposta | K4: Alerta_SLA | L4: Investimento_Campanha_Dia (R$) | M4: Leads_Campanha_Dia | N4: CPL (R$) | O4: Próximo_Follow_Up | P4: Ação_Sugerida | Q4: Alerta_Enviado
A5: L2026-001 | B5: =NOW()-3/24 | C5: João Silva | D5: 5548999990001 | E5: Meta Ads - Estudante | F5: Estudante | G5: Pottker 25 - Kitnet 6 | H5: Visitou | I5: =NOW()-1 | J5: =IFERROR(IF(H5="Novo",(NOW()-B5)*1440,""),"") | K5: =IFS(H5<>"Novo","—",J5="","—",J5>10,"🔴 ATRASADO",TRUE,"🟢 no prazo") | L5: 300 | M5: 60 | N5: =IFERROR(IF(M5>0,L5/M5,0),0) | O5: =IFS(H5="Visitou",I5+1,H5="Fechado","—",AND(H5<>"Fechado",H5<>"Perdido",I5<>""),I5+3,TRUE,"") | P5: =IFS(H5="Novo","Responder agora via WhatsApp",H5="Visitou","Enviar oferta de fechamento em 24h",H5="Fechado","Agendar pedido de review em 15 dias",H5="Perdido","Mover para lista de espera sazonal",TRUE,"Aguardando retorno do lead")
J6: =IFERROR(IF(H6="Novo",(NOW()-B6)*1440,""),"") | K6: =IFS(H6<>"Novo","—",J6="","—",J6>10,"🔴 ATRASADO",TRUE,"🟢 no prazo") | N6: =IFERROR(IF(M6>0,L6/M6,0),0) | O6: =IFS(H6="Visitou",I6+1,H6="Fechado","—",AND(H6<>"Fechado",H6<>"Perdido",I6<>""),I6+3,TRUE,"") | P6: =IFS(H6="Novo","Responder agora via WhatsApp",H6="Visitou","Enviar oferta de fechamento em 24h",H6="Fechado","Agendar pedido de review em 15 dias",H6="Perdido","Mover para lista de espera sazonal",TRUE,"Aguardando retorno do lead")
J7: =IFERROR(IF(H7="Novo",(NOW()-B7)*1440,""),"") | K7: =IFS(H7<>"Novo","—",J7="","—",J7>10,"🔴 ATRASADO",TRUE,"🟢 no prazo") | N7: =IFERROR(IF(M7>0,L7/M7,0),0) | O7: =IFS(H7="Visitou",I7+1,H7="Fechado","—",AND(H7<>"Fechado",H7<>"Perdido",I7<>""),I7+3,TRUE,"") | P7: =IFS(H7="Novo","Responder agora via WhatsApp",H7="Visitou","Enviar oferta de fechamento em 24h",H7="Fechado","Agendar pedido de review em 15 dias",H7="Perdido","Mover para lista de espera sazonal",TRUE,"Aguardando retorno do lead")
J8: =IFERROR(IF(H8="Novo",(NOW()-B8)*1440,""),"") | K8: =IFS(H8<>"Novo","—",J8="","—",J8>10,"🔴 ATRASADO",TRUE,"🟢 no prazo") | N8: =IFERROR(IF(M8>0,L8/M8,0),0) | O8: =IFS(H8="Visitou",I8+1,H8="Fechado","—",AND(H8<>"Fechado",H8<>"Perdido",I8<>""),I8+3,TRUE,"") | P8: =IFS(H8="Novo","Responder agora via WhatsApp",H8="Visitou","Enviar oferta de fechamento em 24h",H8="Fechado","Agendar pedido de review em 15 dias",H8="Perdido","Mover para lista de espera sazonal",TRUE,"Aguardando retorno do lead")
J9: =IFERROR(IF(H9="Novo",(NOW()-B9)*1440,""),"") | K9: =IFS(H9<>"Novo","—",J9="","—",J9>10,"🔴 ATRASADO",TRUE,"🟢 no prazo") | N9: =IFERROR(IF(M9>0,L9/M9,0),0) | O9: =IFS(H9="Visitou",I9+1,H9="Fechado","—",AND(H9<>"Fechado",H9<>"Perdido",I9<>""),I9+3,TRUE,"") | P9: =IFS(H9="Novo","Responder agora via WhatsApp",H9="Visitou","Enviar oferta de fechamento em 24h",H9="Fechado","Agendar pedido de review em 15 dias",H9="Perdido","Mover para lista de espera sazonal",TRUE,"Aguardando retorno do lead")
J10: =IFERROR(IF(H10="Novo",(NOW()-B10)*1440,""),"") | K10: =IFS(H10<>"Novo","—",J10="","—",J10>10,"🔴 ATRASADO",TRUE,"🟢 no prazo") | N10: =IFERROR(IF(M10>0,L10/M10,0),0) | O10: =IFS(H10="Visitou",I10+1,H10="Fechado","—",AND(H10<>"Fechado",H10<>"Perdido",I10<>""),I10+3,TRUE,"") | P10: =IFS(H10="Novo","Responder agora via WhatsApp",H10="Visitou","Enviar oferta de fechamento em 24h",H10="Fechado","Agendar pedido de review em 15 dias",H10="Perdido","Mover para lista de espera sazonal",TRUE,"Aguardando retorno do lead")
J11: =IFERROR(IF(H11="Novo",(NOW()-B11)*1440,""),"") | K11: =IFS(H11<>"Novo","—",J11="","—",J11>10,"🔴 ATRASADO",TRUE,"🟢 no prazo") | N11: =IFERROR(IF(M11>0,L11/M11,0),0) | O11: =IFS(H11="Visitou",I11+1,H11="Fechado","—",AND(H11<>"Fechado",H11<>"Perdido",I11<>""),I11+3,TRUE,"") | P11: =IFS(H11="Novo","Responder agora via WhatsApp",H11="Visitou","Enviar oferta de fechamento em 24h",H11="Fechado","Agendar pedido de review em 15 dias",H11="Perdido","Mover para lista de espera sazonal",TRUE,"Aguardando retorno do lead")
J12: =IFERROR(IF(H12="Novo",(NOW()-B12)*1440,""),"") | K12: =IFS(H12<>"Novo","—",J12="","—",J12>10,"🔴 ATRASADO",TRUE,"🟢 no prazo") | N12: =IFERROR(IF(M12>0,L12/M12,0),0) | O12: =IFS(H12="Visitou",I12+1,H12="Fechado","—",AND(H12<>"Fechado",H12<>"Perdido",I12<>""),I12+3,TRUE,"") | P12: =IFS(H12="Novo","Responder agora via WhatsApp",H12="Visitou","Enviar oferta de fechamento em 24h",H12="Fechado","Agendar pedido de review em 15 dias",H12="Perdido","Mover para lista de espera sazonal",TRUE,"Aguardando retorno do lead")
J13: =IFERROR(IF(H13="Novo",(NOW()-B13)*1440,""),"") | K13: =IFS(H13<>"Novo","—",J13="","—",J13>10,"🔴 ATRASADO",TRUE,"🟢 no prazo") | N13: =IFERROR(IF(M13>0,L13/M13,0),0) | O13: =IFS(H13="Visitou",I13+1,H13="Fechado","—",AND(H13<>"Fechado",H13<>"Perdido",I13<>""),I13+3,TRUE,"") | P13: =IFS(H13="Novo","Responder agora via WhatsApp",H13="Visitou","Enviar oferta de fechamento em 24h",H13="Fechado","Agendar pedido de review em 15 dias",H13="Perdido","Mover para lista de espera sazonal",TRUE,"Aguardando retorno do lead")
J14: =IFERROR(IF(H14="Novo",(NOW()-B14)*1440,""),"") | K14: =IFS(H14<>"Novo","—",J14="","—",J14>10,"🔴 ATRASADO",TRUE,"🟢 no prazo") | N14: =IFERROR(IF(M14>0,L14/M14,0),0) | O14: =IFS(H14="Visitou",I14+1,H14="Fechado","—",AND(H14<>"Fechado",H14<>"Perdido",I14<>""),I14+3,TRUE,"") | P14: =IFS(H14="Novo","Responder agora via WhatsApp",H14="Visitou","Enviar oferta de fechamento em 24h",H14="Fechado","Agendar pedido de review em 15 dias",H14="Perdido","Mover para lista de espera sazonal",TRUE,"Aguardando retorno do lead")
J15: =IFERROR(IF(H15="Novo",(NOW()-B15)*1440,""),"") | K15: =IFS(H15<>"Novo","—",J15="","—",J15>10,"🔴 ATRASADO",TRUE,"🟢 no prazo") | N15: =IFERROR(IF(M15>0,L15/M15,0),0) | O15: =IFS(H15="Visitou",I15+1,H15="Fechado","—",AND(H15<>"Fechado",H15<>"Perdido",I15<>""),I15+3,TRUE,"") | P15: =IFS(H15="Novo","Responder agora via WhatsApp",H15="Visitou","Enviar oferta de fechamento em 24h",H15="Fechado","Agendar pedido de review em 15 dias",H15="Perdido","Mover para lista de espera sazonal",TRUE,"Aguardando retorno do lead")
J16: =IFERROR(IF(H16="Novo",(NOW()-B16)*1440,""),"") | K16: =IFS(H16<>"Novo","—",J16="","—",J16>10,"🔴 ATRASADO",TRUE,"🟢 no prazo") | N16: =IFERROR(IF(M16>0,L16/M16,0),0) | O16: =IFS(H16="Visitou",I16+1,H16="Fechado","—",AND(H16<>"Fechado",H16<>"Perdido",I16<>""),I16+3,TRUE,"") | P16: =IFS(H16="Novo","Responder agora via WhatsApp",H16="Visitou","Enviar oferta de fechamento em 24h",H16="Fechado","Agendar pedido de review em 15 dias",H16="Perdido","Mover para lista de espera sazonal",TRUE,"Aguardando retorno do lead")
J17: =IFERROR(IF(H17="Novo",(NOW()-B17)*1440,""),"") | K17: =IFS(H17<>"Novo","—",J17="","—",J17>10,"🔴 ATRASADO",TRUE,"🟢 no prazo") | N17: =IFERROR(IF(M17>0,L17/M17,0),0) | O17: =IFS(H17="Visitou",I17+1,H17="Fechado","—",AND(H17<>"Fechado",H17<>"Perdido",I17<>""),I17+3,TRUE,"") | P17: =IFS(H17="Novo","Responder agora via WhatsApp",H17="Visitou","Enviar oferta de fechamento em 24h",H17="Fechado","Agendar pedido de review em 15 dias",H17="Perdido","Mover para lista de espera sazonal",TRUE,"Aguardando retorno do lead")
... J60: =IFERROR(IF(H60="Novo",(NOW()-B60)*1440,""),"") | K60: =IFS(H60<>"Novo","—",J60="","—",J60>10,"🔴 ATRASADO",TRUE,"🟢 no prazo") | N60: =IFERROR(IF(M60>0,L60/M60,0),0) | O60: =IFS(H60="Visitou",I60+1,H60="Fechado","—",AND(H60<>"Fechado",H60<>"Perdido",I60<>""),I60+3,TRUE,"") | P60: =IFS(H60="Novo","Responder agora via WhatsApp",H60="Visitou","Enviar oferta de fechamento em 24h",H60="Fechado","Agendar pedido de review em 15 dias",H60="Perdido","Mover para lista de espera sazonal",TRUE,"Aguardando retorno do lead")

Sheet Campanhas
A1: CONTROLE DE CAMPANHAS — Custo por Canal
A2: Uma linha por canal/semana. Preencha só o Investimento — o resto vem da aba Leads.
A4: Semana | B4: Canal | C4: Investimento (R$) | D4: Leads Gerados (auto) | E4: Contratos Fechados (auto) | F4: CPL (R$) | G4: CAC (R$)
A5: 1 | B5: Meta Ads - Estudante | D5: =COUNTIFS(Leads!$E$5:$E$200,B5) | E5: =COUNTIFS(Leads!$E$5:$E$200,B5,Leads!$H$5:$H$200,"Fechado") | F5: =IFERROR(IF(D5>0,C5/D5,0),0) | G5: =IFERROR(IF(E5>0,C5/E5,0),0)
A6: 1 | B6: Meta Ads - Profissional | D6: =COUNTIFS(Leads!$E$5:$E$200,B6) | E6: =COUNTIFS(Leads!$E$5:$E$200,B6,Leads!$H$5:$H$200,"Fechado") | F6: =IFERROR(IF(D6>0,C6/D6,0),0) | G6: =IFERROR(IF(E6>0,C6/E6,0),0)
A7: 1 | B7: Google Ads | D7: =COUNTIFS(Leads!$E$5:$E$200,B7) | E7: =COUNTIFS(Leads!$E$5:$E$200,B7,Leads!$H$5:$H$200,"Fechado") | F7: =IFERROR(IF(D7>0,C7/D7,0),0) | G7: =IFERROR(IF(E7>0,C7/E7,0),0)
A8: 1 | B8: Google Maps | D8: =COUNTIFS(Leads!$E$5:$E$200,B8) | E8: =COUNTIFS(Leads!$E$5:$E$200,B8,Leads!$H$5:$H$200,"Fechado") | F8: =IFERROR(IF(D8>0,C8/D8,0),0) | G8: =IFERROR(IF(E8>0,C8/E8,0),0)
A9: 1 | B9: OLX | D9: =COUNTIFS(Leads!$E$5:$E$200,B9) | E9: =COUNTIFS(Leads!$E$5:$E$200,B9,Leads!$H$5:$H$200,"Fechado") | F9: =IFERROR(IF(D9>0,C9/D9,0),0) | G9: =IFERROR(IF(E9>0,C9/E9,0),0)
A10: 1 | B10: Airbnb | D10: =COUNTIFS(Leads!$E$5:$E$200,B10) | E10: =COUNTIFS(Leads!$E$5:$E$200,B10,Leads!$H$5:$H$200,"Fechado") | F10: =IFERROR(IF(D10>0,C10/D10,0),0) | G10: =IFERROR(IF(E10>0,C10/E10,0),0)
A11: 1 | B11: Grupo Facebook UFSC | D11: =COUNTIFS(Leads!$E$5:$E$200,B11) | E11: =COUNTIFS(Leads!$E$5:$E$200,B11,Leads!$H$5:$H$200,"Fechado") | F11: =IFERROR(IF(D11>0,C11/D11,0),0) | G11: =IFERROR(IF(E11>0,C11/E11,0),0)

Sheet Painel
A1: PAINEL — Central de Leads & Ocupação UFSC
A2: Ocupação ao vivo da Planilha Central via IMPORTRANGE — clique em 'Permitir acesso' na 1ª abertura.
A4: Vacância atual (unid.) | B4: =IMPORTRANGE("https://docs.google.com/spreadsheets/d/1wFoUCZaRPk2V1WbWyI0V4N5EC2yIZb2CNviOCPizaOQ","Dashboard Geral!D9")
A5: Receita mensal máx. do portfólio (R$) | B5: =IMPORTRANGE("https://docs.google.com/spreadsheets/d/1wFoUCZaRPk2V1WbWyI0V4N5EC2yIZb2CNviOCPizaOQ","Dashboard Geral!F9")
A6: Leads em atraso de SLA | B6: =COUNTIF(Leads!K5:K200,"🔴 ATRASADO")
A7: Leads no funil (ativos) | B7: =COUNTIFS(Leads!H5:H200,"<>Fechado",Leads!H5:H200,"<>Perdido",Leads!H5:H200,"<>")
A8: Contratos fechados no mês | B8: =COUNTIF(Leads!H5:H200,"Fechado")
A9: CAC médio (R$) | B9: =IFERROR(AVERAGEIF(Campanhas!G5:G11,">0"),0)
A12: Vacância por imóvel (ao vivo):
A13: Imóvel | B13: Unidades | C13: Vacantes
A14: Pottker 25 | B14: =IMPORTRANGE("https://docs.google.com/spreadsheets/d/1wFoUCZaRPk2V1WbWyI0V4N5EC2yIZb2CNviOCPizaOQ","Dashboard Geral!C6") | C14: =IMPORTRANGE("https://docs.google.com/spreadsheets/d/1wFoUCZaRPk2V1WbWyI0V4N5EC2yIZb2CNviOCPizaOQ","Dashboard Geral!D6")
A15: Milton Sullivan 142 | B15: =IMPORTRANGE("https://docs.google.com/spreadsheets/d/1wFoUCZaRPk2V1WbWyI0V4N5EC2yIZb2CNviOCPizaOQ","Dashboard Geral!C7") | C15: =IMPORTRANGE("https://docs.google.com/spreadsheets/d/1wFoUCZaRPk2V1WbWyI0V4N5EC2yIZb2CNviOCPizaOQ","Dashboard Geral!D7")
A16: Ana Maria Nunes 214 | B16: =IMPORTRANGE("https://docs.google.com/spreadsheets/d/1wFoUCZaRPk2V1WbWyI0V4N5EC2yIZb2CNviOCPizaOQ","Dashboard Geral!C8") | C16: =IMPORTRANGE("https://docs.google.com/spreadsheets/d/1wFoUCZaRPk2V1WbWyI0V4N5EC2yIZb2CNviOCPizaOQ","Dashboard Geral!D8")

Sheet Instruções
A1: COMO USAR ESTA PLANILHA
A3: 1. Aba Leads: a cada novo lead, preencha A–I na primeira linha vazia (L e M com o investimento e nº de leads da campanha do dia, para o CPL).
A4: 2. Coluna K (Alerta_SLA) marca sozinha 🔴 se um lead 'Novo' passar de 10 minutos sem virar 'Respondido'.
A5: 3. Coluna O (Próximo_Follow_Up) calcula a data do próximo contato — 24h após 'Visitou', 3 dias nos demais estágios.
A6: 4. Aba Campanhas: preencha só Investimento (R$) — leads, contratos, CPL e CAC vêm sozinhos da aba Leads.
A7: 5. Aba Painel: na 1ª abertura o Sheets pede autorização do IMPORTRANGE — clique em 'Permitir acesso'.
A8: 6. Alertas automáticos por e-mail: instale o Apps Script (arquivo 'AppsScript-Kitnets-UFSC.txt' na mesma pasta do Drive) em Extensões > Apps Script.
